pdc_event_autodoc/__init__.py
pdc_event_autodoc/doc_view.py
pdc_event_autodoc/documentation.py
pdc_event_autodoc/schemas/doc_schema.py
pdc_event_autodoc-1.0.1.dist-info/WHEEL
pdc_event_autodoc-1.0.1.dist-info/METADATA
pdc_event_autodoc-1.0.1.dist-info/RECORD
