Metadata-Version: 2.1
Name: pdc-event-autodoc
Version: 1.0.1
Summary: Autodoc for socket
Author: Mukhtar
Author-email: mukhtar.syariefudin@gmail.com
Requires-Python: >=3.9,<4.0
Classifier: Programming Language :: Python :: 3
Classifier: Programming Language :: Python :: 3.10
Classifier: Programming Language :: Python :: 3.9
Requires-Dist: pydantic (>=1.10.2,<2.0.0)
